paperagent/__init__.py
paperagent/agent.py
papaeragent-0.1.0.dist-info/LICENSE
papaeragent-0.1.0.dist-info/METADATA
papaeragent-0.1.0.dist-info/WHEEL
papaeragent-0.1.0.dist-info/top_level.txt
papaeragent-0.1.0.dist-info/RECORD
