Metadata-Version: 2.2
Name: papaeragent
Version: 0.1.0
Summary: A package to download arXiv papers and interact with PDFs using Ollama LLM
Home-page: https://github.com/zstar1003/papaeragent
Author: zstar
Author-email: zstar1003@163.com
Classifier: Programming Language :: Python :: 3
Classifier: License :: OSI Approved :: MIT License
Classifier: Operating System :: OS Independent
Requires-Python: >=3.6
License-File: LICENSE
Requires-Dist: requests
Requires-Dist: lxml
Requires-Dist: beautifulsoup4
Requires-Dist: langchain_ollama
Requires-Dist: langchain_community
Dynamic: author
Dynamic: author-email
Dynamic: classifier
Dynamic: description
Dynamic: description-content-type
Dynamic: home-page
Dynamic: requires-dist
Dynamic: requires-python
Dynamic: summary
